zdp_mcp_demo/__init__.py
zdp_mcp_demo-0.1.0.dist-info/WHEEL
zdp_mcp_demo-0.1.0.dist-info/entry_points.txt
zdp_mcp_demo-0.1.0.dist-info/METADATA
zdp_mcp_demo-0.1.0.dist-info/RECORD
