Metadata-Version: 2.3
Name: zdp-mcp-demo
Version: 0.1.0
Summary: Add your description here
Author: zhouyuheng
Author-email: zhouyuheng <957017253@qq.com>
Requires-Dist: mcp[cli]>=1.14.0
Requires-Python: >=3.13
